__init__.py
pmplicense/__init__.py
pmplicense/cli.py
pmplicense/constants.py
pmplicense-0.0.4.dist-info/METADATA
pmplicense-0.0.4.dist-info/WHEEL
pmplicense-0.0.4.dist-info/entry_points.txt
pmplicense-0.0.4.dist-info/top_level.txt
pmplicense-0.0.4.dist-info/RECORD
